CHANGES.txt
LICENSE.txt
README.txt
bootstrap.py
buildout.cfg
setup.py
src/p01/__init__.py
src/p01.tmp.egg-info/PKG-INFO
src/p01.tmp.egg-info/SOURCES.txt
src/p01.tmp.egg-info/dependency_links.txt
src/p01.tmp.egg-info/namespace_packages.txt
src/p01.tmp.egg-info/not-zip-safe
src/p01.tmp.egg-info/requires.txt
src/p01.tmp.egg-info/top_level.txt
src/p01/tmp/README.txt
src/p01/tmp/__init__.py
src/p01/tmp/configure.zcml
src/p01/tmp/default.py
src/p01/tmp/default.zcml
src/p01/tmp/exceptions.py
src/p01/tmp/file.py
src/p01/tmp/interfaces.py
src/p01/tmp/storage.py
src/p01/tmp/tests.py
src/p01/tmp/wsgi.py
src/p01/tmp/generations/__init__.py
src/p01/tmp/generations/configure.zcml