Metadata-Version: 1.0
Name: p01.tmp
Version: 0.6.0
Summary: Persistent transaction observed temporary file supporting zero-copy processing for Zope3
Home-page: http://pypi.python.org/pypi/p01.tmp
Author: Roger Ineichen, Projekt01 GmbH
Author-email: dev@projekt01.ch
License: ZPL 2.1
Keywords: Zope3 z3c p01 temp temporary persistent file zero-copy
Platform: UNKNOWN
Classifier: Development Status :: 4 - Beta
Classifier: Environment :: Web Environment
Classifier: Intended Audience :: Developers
Classifier: License :: OSI Approved :: Zope Public License
Classifier: Programming Language :: Python
Classifier: Natural Language :: English
Classifier: Operating System :: OS Independent
Classifier: Topic :: Internet :: WWW/HTTP
Classifier: Framework :: Zope3
